abbccd/test.py
abbccd-0.0.1.dist-info/LICENSE
abbccd-0.0.1.dist-info/METADATA
abbccd-0.0.1.dist-info/WHEEL
abbccd-0.0.1.dist-info/top_level.txt
abbccd-0.0.1.dist-info/RECORD
