Metadata-Version: 2.1
Name: abbccd
Version: 0.0.1
Summary: A TestPackage Program.
Author-email: SmallWaterSnake <hzk201312@163.com>
Classifier: Programming Language :: Python :: 3
Classifier: License :: OSI Approved :: MIT License
Classifier: Operating System :: OS Independent
Requires-Python: >=3.7
License-File: LICENSE
